abberior/__init__.py
abberior/microscope.py
abberior/user.py
abberior/utils.py
abberior/config/__init__.py
abberior/config/conf.yml
abberior/debug/__init__.py
abberior/debug/conf.yml
abberior/debug/measurement.py
abberior_sted-0.0.3.dist-info/LICENSE
abberior_sted-0.0.3.dist-info/METADATA
abberior_sted-0.0.3.dist-info/WHEEL
abberior_sted-0.0.3.dist-info/top_level.txt
abberior_sted-0.0.3.dist-info/RECORD
