Metadata-Version: 2.1
Name: abberior-sted
Version: 0.0.3
Summary: Interface to Imspector control software for Abberior STED microscopes
License: CC-BY-4.0 license
Project-URL: Documentation, https://github.com/FLClab/Abberior-STED
Project-URL: Source, https://github.com/FLClab/Abberior-STED
Keywords: abberior sted imspector specpy
Classifier: Programming Language :: Python :: 3
Classifier: License :: OSI Approved
Classifier: Operating System :: OS Independent
Classifier: Programming Language :: Python
Classifier: Programming Language :: Python :: 3.8
Classifier: Programming Language :: Python :: 3.9
Classifier: Programming Language :: Python :: 3.10
Classifier: Programming Language :: Python :: 3.11
Classifier: Programming Language :: Python :: 3.12
License-File: LICENSE
Requires-Dist: scikit-image
Requires-Dist: numpy
Requires-Dist: scipy
Requires-Dist: matplotlib
Requires-Dist: pyyaml
